pyecr/__init__.py
pyecr/completers_suggesters.py
pyecr/emoticons.py
pyecr/messages.py
pyecr/pyecr.py
pyecr/style.py
pyecr/utils.py
pyecr-0.0.8.dist-info/METADATA
pyecr-0.0.8.dist-info/WHEEL
pyecr-0.0.8.dist-info/entry_points.txt
pyecr-0.0.8.dist-info/top_level.txt
pyecr-0.0.8.dist-info/RECORD
