Metadata-Version: 2.1
Name: pyecr
Version: 0.0.8
Summary: Utility to help handle the process of pulling images to ECR
Home-page: https://github.com/ualter/pyecr.git
Author: Ualter Otoni Pereira
Author-email: ualter.junior@gmail.com
License: MIT
Keywords: aws,cloud,ecr,boto3,image,docker
Platform: UNKNOWN
Classifier: Development Status :: 3 - Alpha
Classifier: Intended Audience :: Developers
Classifier: Intended Audience :: System Administrators
Classifier: License :: OSI Approved :: MIT License
Classifier: Programming Language :: Python :: 3.7
Classifier: Programming Language :: Python :: 3.8
Requires-Dist: prompt-toolkit (>=2.0.10)
Requires-Dist: boto3 (>=1.18.62)
Requires-Dist: botocore (>=1.21.62)
Requires-Dist: Pygments (>=2.3.1)
Requires-Dist: pytz (>=2019.3)
Requires-Dist: arnparse (>=0.0.2)
Requires-Dist: docker-compose (>=1.29.2)
Requires-Dist: python-dateutil (>=2.8.2)
Requires-Dist: docker (>=5.0.3)
